mbi/__init__.py
mbi/approximate_oracles.py
mbi/callbacks.py
mbi/clique_utils.py
mbi/clique_vector.py
mbi/dataset.py
mbi/domain.py
mbi/einsum.py
mbi/estimation.py
mbi/factor.py
mbi/junction_tree.py
mbi/marginal_loss.py
mbi/marginal_oracles.py
mbi/markov_random_field.py
mbi/experimental/__init__.py
mbi/experimental/mixture_of_products.py
mbi/experimental/public_support.py
mbi-1.0.0.dist-info/licenses/LICENSE
mbi-1.0.0.dist-info/METADATA
mbi-1.0.0.dist-info/WHEEL
mbi-1.0.0.dist-info/top_level.txt
mbi-1.0.0.dist-info/RECORD
