Metadata-Version: 2.4
Name: mbi
Version: 1.0.0
Summary: Marginal-based estimation and inference (with applications to differential privacy)
Author-email: Ryan McKenna <rmckenna21@gmail.com>
License: Apache License 2.0
Project-URL: Homepage, https://github.com/ryan112358/mbi
Project-URL: Repository, https://github.com/ryan112358/mbi
Classifier: Programming Language :: Python :: 3
Classifier: License :: OSI Approved :: Apache Software License
Classifier: Operating System :: OS Independent
Requires-Python: >=3.9
License-File: LICENSE
Requires-Dist: attrs
Requires-Dist: numpy
Requires-Dist: scipy
Requires-Dist: pandas
Requires-Dist: networkx
Requires-Dist: jax
Requires-Dist: jaxlib
Requires-Dist: chex
Requires-Dist: optax
Provides-Extra: dev
Requires-Dist: pytest; extra == "dev"
Requires-Dist: pytype; extra == "dev"
Requires-Dist: parameterized; extra == "dev"
Requires-Dist: yapf; extra == "dev"
Requires-Dist: pylint; extra == "dev"
Requires-Dist: pydocstyle; extra == "dev"
Provides-Extra: docs
Requires-Dist: sphinx; extra == "docs"
Requires-Dist: sphinx-rtd-theme; extra == "docs"
Requires-Dist: myst-parser; extra == "docs"
Dynamic: license-file
